<?xml version="1.0"?>
<property-set xmlns="http://mcc.lip6.fr/">
  <property>
    <id>FamilyReunion-COL-L01200M0120C060P060G030-00</id>
    <description>Automatically generated</description>
    <formula>
      <all-paths>
        <globally>
          <next>
            <integer-le>
              <integer-constant>0</integer-constant>
              <tokens-count>
                <place>l3</place>
              </tokens-count>
            </integer-le>
          </next>
        </globally>
      </all-paths>
    </formula>
  </property>
  <property>
    <id>FamilyReunion-COL-L01200M0120C060P060G030-01</id>
    <description>Automatically generated</description>
    <formula>
      <all-paths>
        <disjunction>
          <integer-le>
            <integer-constant>3</integer-constant>
            <tokens-count>
              <place>l18</place>
            </tokens-count>
          </integer-le>
          <finally>
            <integer-le>
              <integer-constant>2</integer-constant>
              <tokens-count>
                <place>lm2</place>
              </tokens-count>
            </integer-le>
          </finally>
          <finally>
            <integer-le>
              <integer-constant>3</integer-constant>
              <tokens-count>
                <place>l18</place>
              </tokens-count>
            </integer-le>
          </finally>
          <globally>
            <conjunction>
              <globally>
                <integer-le>
                  <tokens-count>
                    <place>m4</place>
                  </tokens-count>
                  <tokens-count>
                    <place>p5</place>
                  </tokens-count>
                </integer-le>
              </globally>
              <negation>
                <globally>
                  <integer-le>
                    <integer-constant>3</integer-constant>
                    <tokens-count>
                      <place>l18</place>
                    </tokens-count>
                  </integer-le>
                </globally>
              </negation>
            </conjunction>
          </globally>
        </disjunction>
      </all-paths>
    </formula>
  </property>
  <property>
    <id>FamilyReunion-COL-L01200M0120C060P060G030-02</id>
    <description>Automatically generated</description>
    <formula>
      <all-paths>
        <until>
          <before>
            <integer-le>
              <tokens-count>
                <place>l28</place>
              </tokens-count>
              <tokens-count>
                <place>l1</place>
              </tokens-count>
            </integer-le>
          </before>
          <reach>
            <until>
              <before>
                <globally>
                  <finally>
                    <integer-le>
                      <tokens-count>
                        <place>l12</place>
                      </tokens-count>
                      <tokens-count>
                        <place>p1</place>
                      </tokens-count>
                    </integer-le>
                  </finally>
                </globally>
              </before>
              <reach>
                <negation>
                  <next>
                    <finally>
                      <integer-le>
                        <tokens-count>
                          <place>lm2</place>
                        </tokens-count>
                        <tokens-count>
                          <place>m7</place>
                        </tokens-count>
                      </integer-le>
                    </finally>
                  </next>
                </negation>
              </reach>
            </until>
          </reach>
        </until>
      </all-paths>
    </formula>
  </property>
  <property>
    <id>FamilyReunion-COL-L01200M0120C060P060G030-03</id>
    <description>Automatically generated</description>
    <formula>
      <all-paths>
        <negation>
          <next>
            <finally>
              <globally>
                <until>
                  <before>
                    <next>
                      <integer-le>
                        <integer-constant>2</integer-constant>
                        <tokens-count>
                          <place>l19</place>
                        </tokens-count>
                      </integer-le>
                    </next>
                  </before>
                  <reach>
                    <conjunction>
                      <negation>
                        <integer-le>
                          <integer-constant>2</integer-constant>
                          <tokens-count>
                            <place>l19</place>
                          </tokens-count>
                        </integer-le>
                      </negation>
                      <globally>
                        <negation>
                          <integer-le>
                            <tokens-count>
                              <place>l30</place>
                            </tokens-count>
                            <tokens-count>
                              <place>l36</place>
                            </tokens-count>
                          </integer-le>
                        </negation>
                      </globally>
                    </conjunction>
                  </reach>
                </until>
              </globally>
            </finally>
          </next>
        </negation>
      </all-paths>
    </formula>
  </property>
  <property>
    <id>FamilyReunion-COL-L01200M0120C060P060G030-04</id>
    <description>Automatically generated</description>
    <formula>
      <all-paths>
        <globally>
          <finally>
            <next>
              <disjunction>
                <globally>
                  <integer-le>
                    <tokens-count>
                      <place>l8</place>
                    </tokens-count>
                    <tokens-count>
                      <place>l22</place>
                    </tokens-count>
                  </integer-le>
                </globally>
                <globally>
                  <until>
                    <before>
                      <globally>
                        <integer-le>
                          <tokens-count>
                            <place>l17</place>
                          </tokens-count>
                          <tokens-count>
                            <place>l21</place>
                          </tokens-count>
                        </integer-le>
                      </globally>
                    </before>
                    <reach>
                      <integer-le>
                        <integer-constant>1</integer-constant>
                        <tokens-count>
                          <place>l15</place>
                        </tokens-count>
                      </integer-le>
                    </reach>
                  </until>
                </globally>
              </disjunction>
            </next>
          </finally>
        </globally>
      </all-paths>
    </formula>
  </property>
  <property>
    <id>FamilyReunion-COL-L01200M0120C060P060G030-05</id>
    <description>Automatically generated</description>
    <formula>
      <all-paths>
        <globally>
          <finally>
            <until>
              <before>
                <integer-le>
                  <tokens-count>
                    <place>l8</place>
                  </tokens-count>
                  <tokens-count>
                    <place>c5</place>
                  </tokens-count>
                </integer-le>
              </before>
              <reach>
                <globally>
                  <integer-le>
                    <integer-constant>3</integer-constant>
                    <tokens-count>
                      <place>p3</place>
                    </tokens-count>
                  </integer-le>
                </globally>
              </reach>
            </until>
          </finally>
        </globally>
      </all-paths>
    </formula>
  </property>
  <property>
    <id>FamilyReunion-COL-L01200M0120C060P060G030-06</id>
    <description>Automatically generated</description>
    <formula>
      <all-paths>
        <disjunction>
          <finally>
            <conjunction>
              <integer-le>
                <integer-constant>2</integer-constant>
                <tokens-count>
                  <place>p8</place>
                </tokens-count>
              </integer-le>
              <integer-le>
                <integer-constant>0</integer-constant>
                <tokens-count>
                  <place>l9</place>
                </tokens-count>
              </integer-le>
            </conjunction>
          </finally>
          <globally>
            <until>
              <before>
                <next>
                  <finally>
                    <integer-le>
                      <integer-constant>1</integer-constant>
                      <tokens-count>
                        <place>l16</place>
                      </tokens-count>
                    </integer-le>
                  </finally>
                </next>
              </before>
              <reach>
                <globally>
                  <negation>
                    <next>
                      <integer-le>
                        <integer-constant>0</integer-constant>
                        <tokens-count>
                          <place>l9</place>
                        </tokens-count>
                      </integer-le>
                    </next>
                  </negation>
                </globally>
              </reach>
            </until>
          </globally>
        </disjunction>
      </all-paths>
    </formula>
  </property>
  <property>
    <id>FamilyReunion-COL-L01200M0120C060P060G030-07</id>
    <description>Automatically generated</description>
    <formula>
      <all-paths>
        <until>
          <before>
            <negation>
              <finally>
                <integer-le>
                  <tokens-count>
                    <place>m5</place>
                  </tokens-count>
                  <tokens-count>
                    <place>l25</place>
                  </tokens-count>
                </integer-le>
              </finally>
            </negation>
          </before>
          <reach>
            <integer-le>
              <integer-constant>3</integer-constant>
              <tokens-count>
                <place>l28</place>
              </tokens-count>
            </integer-le>
          </reach>
        </until>
      </all-paths>
    </formula>
  </property>
  <property>
    <id>FamilyReunion-COL-L01200M0120C060P060G030-08</id>
    <description>Automatically generated</description>
    <formula>
      <all-paths>
        <negation>
          <disjunction>
            <until>
              <before>
                <negation>
                  <integer-le>
                    <integer-constant>3</integer-constant>
                    <tokens-count>
                      <place>p7</place>
                    </tokens-count>
                  </integer-le>
                </negation>
              </before>
              <reach>
                <next>
                  <integer-le>
                    <tokens-count>
                      <place>l9</place>
                    </tokens-count>
                    <tokens-count>
                      <place>lc2</place>
                    </tokens-count>
                  </integer-le>
                </next>
              </reach>
            </until>
            <next>
              <until>
                <before>
                  <integer-le>
                    <tokens-count>
                      <place>l9</place>
                    </tokens-count>
                    <tokens-count>
                      <place>lc2</place>
                    </tokens-count>
                  </integer-le>
                </before>
                <reach>
                  <next>
                    <integer-le>
                      <integer-constant>0</integer-constant>
                      <tokens-count>
                        <place>l31</place>
                      </tokens-count>
                    </integer-le>
                  </next>
                </reach>
              </until>
            </next>
          </disjunction>
        </negation>
      </all-paths>
    </formula>
  </property>
  <property>
    <id>FamilyReunion-COL-L01200M0120C060P060G030-09</id>
    <description>Automatically generated</description>
    <formula>
      <all-paths>
        <globally>
          <conjunction>
            <next>
              <integer-le>
                <integer-constant>3</integer-constant>
                <tokens-count>
                  <place>l12</place>
                </tokens-count>
              </integer-le>
            </next>
            <globally>
              <disjunction>
                <integer-le>
                  <integer-constant>2</integer-constant>
                  <tokens-count>
                    <place>g1</place>
                  </tokens-count>
                </integer-le>
                <next>
                  <integer-le>
                    <integer-constant>3</integer-constant>
                    <tokens-count>
                      <place>l12</place>
                    </tokens-count>
                  </integer-le>
                </next>
              </disjunction>
            </globally>
          </conjunction>
        </globally>
      </all-paths>
    </formula>
  </property>
  <property>
    <id>FamilyReunion-COL-L01200M0120C060P060G030-10</id>
    <description>Automatically generated</description>
    <formula>
      <all-paths>
        <next>
          <next>
            <finally>
              <until>
                <before>
                  <integer-le>
                    <tokens-count>
                      <place>m5</place>
                    </tokens-count>
                    <tokens-count>
                      <place>m4</place>
                    </tokens-count>
                  </integer-le>
                </before>
                <reach>
                  <integer-le>
                    <tokens-count>
                      <place>l40</place>
                    </tokens-count>
                    <tokens-count>
                      <place>l8</place>
                    </tokens-count>
                  </integer-le>
                </reach>
              </until>
            </finally>
          </next>
        </next>
      </all-paths>
    </formula>
  </property>
  <property>
    <id>FamilyReunion-COL-L01200M0120C060P060G030-11</id>
    <description>Automatically generated</description>
    <formula>
      <all-paths>
        <until>
          <before>
            <until>
              <before>
                <next>
                  <finally>
                    <integer-le>
                      <integer-constant>3</integer-constant>
                      <tokens-count>
                        <place>l4</place>
                      </tokens-count>
                    </integer-le>
                  </finally>
                </next>
              </before>
              <reach>
                <integer-le>
                  <tokens-count>
                    <place>g4</place>
                  </tokens-count>
                  <tokens-count>
                    <place>l19</place>
                  </tokens-count>
                </integer-le>
              </reach>
            </until>
          </before>
          <reach>
            <integer-le>
              <tokens-count>
                <place>l40</place>
              </tokens-count>
              <tokens-count>
                <place>lg0</place>
              </tokens-count>
            </integer-le>
          </reach>
        </until>
      </all-paths>
    </formula>
  </property>
  <property>
    <id>FamilyReunion-COL-L01200M0120C060P060G030-12</id>
    <description>Automatically generated</description>
    <formula>
      <all-paths>
        <conjunction>
          <disjunction>
            <integer-le>
              <tokens-count>
                <place>m11</place>
              </tokens-count>
              <tokens-count>
                <place>c6</place>
              </tokens-count>
            </integer-le>
            <finally>
              <negation>
                <globally>
                  <disjunction>
                    <negation>
                      <integer-le>
                        <tokens-count>
                          <place>m11</place>
                        </tokens-count>
                        <tokens-count>
                          <place>c6</place>
                        </tokens-count>
                      </integer-le>
                    </negation>
                    <finally>
                      <integer-le>
                        <tokens-count>
                          <place>p9</place>
                        </tokens-count>
                        <tokens-count>
                          <place>l1</place>
                        </tokens-count>
                      </integer-le>
                    </finally>
                  </disjunction>
                </globally>
              </negation>
            </finally>
          </disjunction>
          <disjunction>
            <integer-le>
              <tokens-count>
                <place>m11</place>
              </tokens-count>
              <tokens-count>
                <place>c6</place>
              </tokens-count>
            </integer-le>
            <finally>
              <integer-le>
                <tokens-count>
                  <place>p9</place>
                </tokens-count>
                <tokens-count>
                  <place>l1</place>
                </tokens-count>
              </integer-le>
            </finally>
          </disjunction>
        </conjunction>
      </all-paths>
    </formula>
  </property>
  <property>
    <id>FamilyReunion-COL-L01200M0120C060P060G030-13</id>
    <description>Automatically generated</description>
    <formula>
      <all-paths>
        <negation>
          <until>
            <before>
              <globally>
                <integer-le>
                  <tokens-count>
                    <place>ml1</place>
                  </tokens-count>
                  <tokens-count>
                    <place>g2</place>
                  </tokens-count>
                </integer-le>
              </globally>
            </before>
            <reach>
              <globally>
                <integer-le>
                  <tokens-count>
                    <place>m4</place>
                  </tokens-count>
                  <tokens-count>
                    <place>l25</place>
                  </tokens-count>
                </integer-le>
              </globally>
            </reach>
          </until>
        </negation>
      </all-paths>
    </formula>
  </property>
  <property>
    <id>FamilyReunion-COL-L01200M0120C060P060G030-14</id>
    <description>Automatically generated</description>
    <formula>
      <all-paths>
        <until>
          <before>
            <disjunction>
              <integer-le>
                <tokens-count>
                  <place>lc0</place>
                </tokens-count>
                <tokens-count>
                  <place>l7</place>
                </tokens-count>
              </integer-le>
              <globally>
                <integer-le>
                  <tokens-count>
                    <place>c5</place>
                  </tokens-count>
                  <tokens-count>
                    <place>c6</place>
                  </tokens-count>
                </integer-le>
              </globally>
              <conjunction>
                <negation>
                  <integer-le>
                    <tokens-count>
                      <place>l2</place>
                    </tokens-count>
                    <tokens-count>
                      <place>lp1</place>
                    </tokens-count>
                  </integer-le>
                </negation>
                <next>
                  <globally>
                    <next>
                      <integer-le>
                        <integer-constant>3</integer-constant>
                        <tokens-count>
                          <place>l4</place>
                        </tokens-count>
                      </integer-le>
                    </next>
                  </globally>
                </next>
              </conjunction>
            </disjunction>
          </before>
          <reach>
            <integer-le>
              <integer-constant>3</integer-constant>
              <tokens-count>
                <place>l4</place>
              </tokens-count>
            </integer-le>
          </reach>
        </until>
      </all-paths>
    </formula>
  </property>
  <property>
    <id>FamilyReunion-COL-L01200M0120C060P060G030-15</id>
    <description>Automatically generated</description>
    <formula>
      <all-paths>
        <disjunction>
          <conjunction>
            <integer-le>
              <integer-constant>1</integer-constant>
              <tokens-count>
                <place>p7</place>
              </tokens-count>
            </integer-le>
            <next>
              <integer-le>
                <integer-constant>1</integer-constant>
                <tokens-count>
                  <place>lp0</place>
                </tokens-count>
              </integer-le>
            </next>
          </conjunction>
          <finally>
            <next>
              <integer-le>
                <integer-constant>1</integer-constant>
                <tokens-count>
                  <place>p7</place>
                </tokens-count>
              </integer-le>
            </next>
          </finally>
        </disjunction>
      </all-paths>
    </formula>
  </property>
</property-set>
