<?xml version="1.0"?>
<property-set xmlns="http://mcc.lip6.fr/">
  <property>
    <id>DotAndBoxes-COL-5-CTLFireability-00</id>
    <description>Automatically generated</description>
    <formula>
      <all-paths>
        <globally>
          <exists-path>
            <globally>
              <negation>
                <conjunction>
                  <is-fireable>
                    <transition>Win2V</transition>
                  </is-fireable>
                  <is-fireable>
                    <transition>Win2H</transition>
                  </is-fireable>
                </conjunction>
              </negation>
            </globally>
          </exists-path>
        </globally>
      </all-paths>
    </formula>
  </property>
  <property>
    <id>DotAndBoxes-COL-5-CTLFireability-01</id>
    <description>Automatically generated</description>
    <formula>
      <disjunction>
        <exists-path>
          <globally>
            <disjunction>
              <is-fireable>
                <transition>Win2V</transition>
              </is-fireable>
              <is-fireable>
                <transition>AWin</transition>
              </is-fireable>
            </disjunction>
          </globally>
        </exists-path>
        <exists-path>
          <next>
            <conjunction>
              <negation>
                <negation>
                  <is-fireable>
                    <transition>AWin</transition>
                  </is-fireable>
                </negation>
              </negation>
              <exists-path>
                <next>
                  <is-fireable>
                    <transition>Play</transition>
                  </is-fireable>
                </next>
              </exists-path>
            </conjunction>
          </next>
        </exists-path>
      </disjunction>
    </formula>
  </property>
  <property>
    <id>DotAndBoxes-COL-5-CTLFireability-02</id>
    <description>Automatically generated</description>
    <formula>
      <disjunction>
        <is-fireable>
          <transition>Lose1</transition>
        </is-fireable>
        <disjunction>
          <exists-path>
            <globally>
              <disjunction>
                <negation>
                  <is-fireable>
                    <transition>Win2H</transition>
                  </is-fireable>
                </negation>
                <disjunction>
                  <is-fireable>
                    <transition>Lose2</transition>
                  </is-fireable>
                  <is-fireable>
                    <transition>AWin</transition>
                  </is-fireable>
                </disjunction>
              </disjunction>
            </globally>
          </exists-path>
          <disjunction>
            <exists-path>
              <next>
                <disjunction>
                  <is-fireable>
                    <transition>Win2H</transition>
                  </is-fireable>
                  <is-fireable>
                    <transition>Lose1</transition>
                  </is-fireable>
                </disjunction>
              </next>
            </exists-path>
            <conjunction>
              <negation>
                <conjunction>
                  <is-fireable>
                    <transition>Win2V</transition>
                  </is-fireable>
                  <is-fireable>
                    <transition>Play</transition>
                  </is-fireable>
                </conjunction>
              </negation>
              <conjunction>
                <negation>
                  <is-fireable>
                    <transition>Lose1</transition>
                  </is-fireable>
                </negation>
                <conjunction>
                  <is-fireable>
                    <transition>Lose2</transition>
                  </is-fireable>
                  <is-fireable>
                    <transition>Win1</transition>
                  </is-fireable>
                </conjunction>
              </conjunction>
            </conjunction>
          </disjunction>
        </disjunction>
      </disjunction>
    </formula>
  </property>
  <property>
    <id>DotAndBoxes-COL-5-CTLFireability-03</id>
    <description>Automatically generated</description>
    <formula>
      <negation>
        <negation>
          <disjunction>
            <exists-path>
              <next>
                <is-fireable>
                  <transition>AWin</transition>
                </is-fireable>
              </next>
            </exists-path>
            <conjunction>
              <disjunction>
                <negation>
                  <is-fireable>
                    <transition>Lose1</transition>
                  </is-fireable>
                </negation>
                <is-fireable>
                  <transition>Lose2</transition>
                </is-fireable>
              </disjunction>
              <conjunction>
                <negation>
                  <is-fireable>
                    <transition>Lose1</transition>
                  </is-fireable>
                </negation>
                <disjunction>
                  <is-fireable>
                    <transition>Lose2</transition>
                  </is-fireable>
                  <is-fireable>
                    <transition>Win2V</transition>
                  </is-fireable>
                </disjunction>
              </conjunction>
            </conjunction>
          </disjunction>
        </negation>
      </negation>
    </formula>
  </property>
  <property>
    <id>DotAndBoxes-COL-5-CTLFireability-04</id>
    <description>Automatically generated</description>
    <formula>
      <negation>
        <negation>
          <all-paths>
            <next>
              <disjunction>
                <conjunction>
                  <is-fireable>
                    <transition>Win2H</transition>
                  </is-fireable>
                  <is-fireable>
                    <transition>Win2H</transition>
                  </is-fireable>
                </conjunction>
                <is-fireable>
                  <transition>Lose1</transition>
                </is-fireable>
              </disjunction>
            </next>
          </all-paths>
        </negation>
      </negation>
    </formula>
  </property>
  <property>
    <id>DotAndBoxes-COL-5-CTLFireability-05</id>
    <description>Automatically generated</description>
    <formula>
      <all-paths>
        <next>
          <exists-path>
            <globally>
              <conjunction>
                <disjunction>
                  <is-fireable>
                    <transition>Play</transition>
                  </is-fireable>
                  <is-fireable>
                    <transition>Win2H</transition>
                  </is-fireable>
                </disjunction>
                <disjunction>
                  <is-fireable>
                    <transition>Lose1</transition>
                  </is-fireable>
                  <is-fireable>
                    <transition>Play</transition>
                  </is-fireable>
                </disjunction>
              </conjunction>
            </globally>
          </exists-path>
        </next>
      </all-paths>
    </formula>
  </property>
  <property>
    <id>DotAndBoxes-COL-5-CTLFireability-06</id>
    <description>Automatically generated</description>
    <formula>
      <is-fireable>
        <transition>NoWin</transition>
      </is-fireable>
    </formula>
  </property>
  <property>
    <id>DotAndBoxes-COL-5-CTLFireability-07</id>
    <description>Automatically generated</description>
    <formula>
      <exists-path>
        <next>
          <exists-path>
            <globally>
              <is-fireable>
                <transition>Win2V</transition>
              </is-fireable>
            </globally>
          </exists-path>
        </next>
      </exists-path>
    </formula>
  </property>
  <property>
    <id>DotAndBoxes-COL-5-CTLFireability-08</id>
    <description>Automatically generated</description>
    <formula>
      <all-paths>
        <next>
          <negation>
            <is-fireable>
              <transition>Win2H</transition>
            </is-fireable>
          </negation>
        </next>
      </all-paths>
    </formula>
  </property>
  <property>
    <id>DotAndBoxes-COL-5-CTLFireability-09</id>
    <description>Automatically generated</description>
    <formula>
      <conjunction>
        <negation>
          <negation>
            <is-fireable>
              <transition>Lose2</transition>
            </is-fireable>
          </negation>
        </negation>
        <negation>
          <negation>
            <is-fireable>
              <transition>Win2H</transition>
            </is-fireable>
          </negation>
        </negation>
      </conjunction>
    </formula>
  </property>
  <property>
    <id>DotAndBoxes-COL-5-CTLFireability-10</id>
    <description>Automatically generated</description>
    <formula>
      <disjunction>
        <all-paths>
          <until>
            <before>
              <all-paths>
                <finally>
                  <is-fireable>
                    <transition>Win1</transition>
                  </is-fireable>
                </finally>
              </all-paths>
            </before>
            <reach>
              <disjunction>
                <is-fireable>
                  <transition>NoWin</transition>
                </is-fireable>
                <disjunction>
                  <is-fireable>
                    <transition>NoWin</transition>
                  </is-fireable>
                  <is-fireable>
                    <transition>Play</transition>
                  </is-fireable>
                </disjunction>
              </disjunction>
            </reach>
          </until>
        </all-paths>
        <all-paths>
          <globally>
            <all-paths>
              <until>
                <before>
                  <is-fireable>
                    <transition>Win2H</transition>
                  </is-fireable>
                </before>
                <reach>
                  <is-fireable>
                    <transition>Win2H</transition>
                  </is-fireable>
                </reach>
              </until>
            </all-paths>
          </globally>
        </all-paths>
      </disjunction>
    </formula>
  </property>
  <property>
    <id>DotAndBoxes-COL-5-CTLFireability-11</id>
    <description>Automatically generated</description>
    <formula>
      <disjunction>
        <all-paths>
          <next>
            <negation>
              <negation>
                <is-fireable>
                  <transition>Play</transition>
                </is-fireable>
              </negation>
            </negation>
          </next>
        </all-paths>
        <is-fireable>
          <transition>NoWin</transition>
        </is-fireable>
      </disjunction>
    </formula>
  </property>
  <property>
    <id>DotAndBoxes-COL-5-CTLFireability-12</id>
    <description>Automatically generated</description>
    <formula>
      <disjunction>
        <is-fireable>
          <transition>AWin</transition>
        </is-fireable>
        <conjunction>
          <conjunction>
            <disjunction>
              <all-paths>
                <globally>
                  <is-fireable>
                    <transition>Win2V</transition>
                  </is-fireable>
                </globally>
              </all-paths>
              <all-paths>
                <finally>
                  <is-fireable>
                    <transition>Play</transition>
                  </is-fireable>
                </finally>
              </all-paths>
            </disjunction>
            <exists-path>
              <until>
                <before>
                  <is-fireable>
                    <transition>Lose2</transition>
                  </is-fireable>
                </before>
                <reach>
                  <is-fireable>
                    <transition>AWin</transition>
                  </is-fireable>
                </reach>
              </until>
            </exists-path>
          </conjunction>
          <negation>
            <negation>
              <disjunction>
                <disjunction>
                  <is-fireable>
                    <transition>Win1</transition>
                  </is-fireable>
                  <is-fireable>
                    <transition>Win1</transition>
                  </is-fireable>
                </disjunction>
                <is-fireable>
                  <transition>Win2V</transition>
                </is-fireable>
              </disjunction>
            </negation>
          </negation>
        </conjunction>
      </disjunction>
    </formula>
  </property>
  <property>
    <id>DotAndBoxes-COL-5-CTLFireability-13</id>
    <description>Automatically generated</description>
    <formula>
      <is-fireable>
        <transition>Play</transition>
      </is-fireable>
    </formula>
  </property>
  <property>
    <id>DotAndBoxes-COL-5-CTLFireability-14</id>
    <description>Automatically generated</description>
    <formula>
      <disjunction>
        <exists-path>
          <finally>
            <exists-path>
              <next>
                <is-fireable>
                  <transition>Lose2</transition>
                </is-fireable>
              </next>
            </exists-path>
          </finally>
        </exists-path>
        <disjunction>
          <conjunction>
            <all-paths>
              <next>
                <negation>
                  <is-fireable>
                    <transition>Win2V</transition>
                  </is-fireable>
                </negation>
              </next>
            </all-paths>
            <conjunction>
              <exists-path>
                <globally>
                  <is-fireable>
                    <transition>Win2V</transition>
                  </is-fireable>
                </globally>
              </exists-path>
              <disjunction>
                <disjunction>
                  <is-fireable>
                    <transition>Win2H</transition>
                  </is-fireable>
                  <is-fireable>
                    <transition>Play</transition>
                  </is-fireable>
                </disjunction>
                <negation>
                  <is-fireable>
                    <transition>AWin</transition>
                  </is-fireable>
                </negation>
              </disjunction>
            </conjunction>
          </conjunction>
          <negation>
            <disjunction>
              <all-paths>
                <globally>
                  <is-fireable>
                    <transition>AWin</transition>
                  </is-fireable>
                </globally>
              </all-paths>
              <negation>
                <negation>
                  <is-fireable>
                    <transition>Lose1</transition>
                  </is-fireable>
                </negation>
              </negation>
            </disjunction>
          </negation>
        </disjunction>
      </disjunction>
    </formula>
  </property>
  <property>
    <id>DotAndBoxes-COL-5-CTLFireability-15</id>
    <description>Automatically generated</description>
    <formula>
      <all-paths>
        <until>
          <before>
            <exists-path>
              <finally>
                <disjunction>
                  <is-fireable>
                    <transition>AWin</transition>
                  </is-fireable>
                  <is-fireable>
                    <transition>NoWin</transition>
                  </is-fireable>
                </disjunction>
              </finally>
            </exists-path>
          </before>
          <reach>
            <disjunction>
              <disjunction>
                <negation>
                  <is-fireable>
                    <transition>Win1</transition>
                  </is-fireable>
                </negation>
                <negation>
                  <is-fireable>
                    <transition>Lose2</transition>
                  </is-fireable>
                </negation>
              </disjunction>
              <disjunction>
                <disjunction>
                  <is-fireable>
                    <transition>Win1</transition>
                  </is-fireable>
                  <is-fireable>
                    <transition>Win2H</transition>
                  </is-fireable>
                </disjunction>
                <conjunction>
                  <is-fireable>
                    <transition>Lose2</transition>
                  </is-fireable>
                  <is-fireable>
                    <transition>Win1</transition>
                  </is-fireable>
                </conjunction>
              </disjunction>
            </disjunction>
          </reach>
        </until>
      </all-paths>
    </formula>
  </property>
</property-set>
