<?xml version="1.0"?>
<property-set xmlns="http://mcc.lip6.fr/">
  <property>
    <id>LamportFastMutEx-COL-8-CTLFireability-00</id>
    <description>Automatically generated</description>
    <formula>
      <disjunction>
        <all-paths>
          <until>
            <before>
              <conjunction>
                <conjunction>
                  <is-fireable>
                    <transition>T-forod_13</transition>
                  </is-fireable>
                  <is-fireable>
                    <transition>T-yne0_4</transition>
                  </is-fireable>
                </conjunction>
                <conjunction>
                  <is-fireable>
                    <transition>T-awaity</transition>
                  </is-fireable>
                  <is-fireable>
                    <transition>T-setbi_11</transition>
                  </is-fireable>
                </conjunction>
              </conjunction>
            </before>
            <reach>
              <exists-path>
                <globally>
                  <is-fireable>
                    <transition>T-ynei_15</transition>
                  </is-fireable>
                </globally>
              </exists-path>
            </reach>
          </until>
        </all-paths>
        <exists-path>
          <globally>
            <all-paths>
              <finally>
                <is-fireable>
                  <transition>T-xeqi_10</transition>
                </is-fireable>
              </finally>
            </all-paths>
          </globally>
        </exists-path>
      </disjunction>
    </formula>
  </property>
  <property>
    <id>LamportFastMutEx-COL-8-CTLFireability-01</id>
    <description>Automatically generated</description>
    <formula>
      <all-paths>
        <globally>
          <all-paths>
            <globally>
              <disjunction>
                <disjunction>
                  <is-fireable>
                    <transition>T-xeqi_10</transition>
                  </is-fireable>
                  <is-fireable>
                    <transition>T-yeqi_15</transition>
                  </is-fireable>
                </disjunction>
                <negation>
                  <is-fireable>
                    <transition>T-awaity</transition>
                  </is-fireable>
                </negation>
              </disjunction>
            </globally>
          </all-paths>
        </globally>
      </all-paths>
    </formula>
  </property>
  <property>
    <id>LamportFastMutEx-COL-8-CTLFireability-02</id>
    <description>Automatically generated</description>
    <formula>
      <conjunction>
        <all-paths>
          <next>
            <all-paths>
              <finally>
                <disjunction>
                  <is-fireable>
                    <transition>T-setbi_5</transition>
                  </is-fireable>
                  <is-fireable>
                    <transition>T-fordo_12</transition>
                  </is-fireable>
                </disjunction>
              </finally>
            </all-paths>
          </next>
        </all-paths>
        <exists-path>
          <next>
            <disjunction>
              <exists-path>
                <next>
                  <is-fireable>
                    <transition>T-yeqi_15</transition>
                  </is-fireable>
                </next>
              </exists-path>
              <negation>
                <disjunction>
                  <is-fireable>
                    <transition>T-sety0_23</transition>
                  </is-fireable>
                  <is-fireable>
                    <transition>T-fordo_12</transition>
                  </is-fireable>
                </disjunction>
              </negation>
            </disjunction>
          </next>
        </exists-path>
      </conjunction>
    </formula>
  </property>
  <property>
    <id>LamportFastMutEx-COL-8-CTLFireability-03</id>
    <description>Automatically generated</description>
    <formula>
      <exists-path>
        <globally>
          <exists-path>
            <finally>
              <conjunction>
                <conjunction>
                  <is-fireable>
                    <transition>T-await_13</transition>
                  </is-fireable>
                  <is-fireable>
                    <transition>T-setbi_5</transition>
                  </is-fireable>
                </conjunction>
                <conjunction>
                  <is-fireable>
                    <transition>T-yne0_4</transition>
                  </is-fireable>
                  <is-fireable>
                    <transition>T-yeq0_4</transition>
                  </is-fireable>
                </conjunction>
              </conjunction>
            </finally>
          </exists-path>
        </globally>
      </exists-path>
    </formula>
  </property>
  <property>
    <id>LamportFastMutEx-COL-8-CTLFireability-04</id>
    <description>Automatically generated</description>
    <formula>
      <negation>
        <exists-path>
          <globally>
            <disjunction>
              <all-paths>
                <next>
                  <is-fireable>
                    <transition>T-forod_13</transition>
                  </is-fireable>
                </next>
              </all-paths>
              <negation>
                <disjunction>
                  <is-fireable>
                    <transition>T-await_13</transition>
                  </is-fireable>
                  <is-fireable>
                    <transition>T-forod_13</transition>
                  </is-fireable>
                </disjunction>
              </negation>
            </disjunction>
          </globally>
        </exists-path>
      </negation>
    </formula>
  </property>
  <property>
    <id>LamportFastMutEx-COL-8-CTLFireability-05</id>
    <description>Automatically generated</description>
    <formula>
      <exists-path>
        <globally>
          <all-paths>
            <finally>
              <disjunction>
                <disjunction>
                  <is-fireable>
                    <transition>T-setbi_24</transition>
                  </is-fireable>
                  <is-fireable>
                    <transition>T-fordo_12</transition>
                  </is-fireable>
                </disjunction>
                <conjunction>
                  <is-fireable>
                    <transition>T-sety_9</transition>
                  </is-fireable>
                  <is-fireable>
                    <transition>T-setbi_24</transition>
                  </is-fireable>
                </conjunction>
              </disjunction>
            </finally>
          </all-paths>
        </globally>
      </exists-path>
    </formula>
  </property>
  <property>
    <id>LamportFastMutEx-COL-8-CTLFireability-06</id>
    <description>Automatically generated</description>
    <formula>
      <disjunction>
        <conjunction>
          <exists-path>
            <until>
              <before>
                <is-fireable>
                  <transition>T-setbi_2</transition>
                </is-fireable>
              </before>
              <reach>
                <is-fireable>
                  <transition>T-sety_9</transition>
                </is-fireable>
              </reach>
            </until>
          </exists-path>
          <negation>
            <disjunction>
              <all-paths>
                <finally>
                  <is-fireable>
                    <transition>T-setbi_11</transition>
                  </is-fireable>
                </finally>
              </all-paths>
              <conjunction>
                <negation>
                  <is-fireable>
                    <transition>T-xnei_10</transition>
                  </is-fireable>
                </negation>
                <is-fireable>
                  <transition>T-awaity</transition>
                </is-fireable>
              </conjunction>
            </disjunction>
          </negation>
        </conjunction>
        <negation>
          <exists-path>
            <finally>
              <all-paths>
                <globally>
                  <is-fireable>
                    <transition>T-sety0_23</transition>
                  </is-fireable>
                </globally>
              </all-paths>
            </finally>
          </exists-path>
        </negation>
      </disjunction>
    </formula>
  </property>
  <property>
    <id>LamportFastMutEx-COL-8-CTLFireability-07</id>
    <description>Automatically generated</description>
    <formula>
      <all-paths>
        <until>
          <before>
            <all-paths>
              <finally>
                <conjunction>
                  <is-fireable>
                    <transition>T-sety_9</transition>
                  </is-fireable>
                  <is-fireable>
                    <transition>T-ynei_15</transition>
                  </is-fireable>
                </conjunction>
              </finally>
            </all-paths>
          </before>
          <reach>
            <all-paths>
              <globally>
                <conjunction>
                  <is-fireable>
                    <transition>T-yne0_4</transition>
                  </is-fireable>
                  <is-fireable>
                    <transition>T-forod_13</transition>
                  </is-fireable>
                </conjunction>
              </globally>
            </all-paths>
          </reach>
        </until>
      </all-paths>
    </formula>
  </property>
  <property>
    <id>LamportFastMutEx-COL-8-CTLFireability-08</id>
    <description>Automatically generated</description>
    <formula>
      <disjunction>
        <all-paths>
          <globally>
            <disjunction>
              <negation>
                <disjunction>
                  <is-fireable>
                    <transition>T-awaity</transition>
                  </is-fireable>
                  <is-fireable>
                    <transition>T-setbi_5</transition>
                  </is-fireable>
                </disjunction>
              </negation>
              <all-paths>
                <next>
                  <is-fireable>
                    <transition>T-yeqi_15</transition>
                  </is-fireable>
                </next>
              </all-paths>
            </disjunction>
          </globally>
        </all-paths>
        <negation>
          <exists-path>
            <finally>
              <is-fireable>
                <transition>T-awaity</transition>
              </is-fireable>
            </finally>
          </exists-path>
        </negation>
      </disjunction>
    </formula>
  </property>
  <property>
    <id>LamportFastMutEx-COL-8-CTLFireability-09</id>
    <description>Automatically generated</description>
    <formula>
      <disjunction>
        <exists-path>
          <globally>
            <disjunction>
              <disjunction>
                <negation>
                  <is-fireable>
                    <transition>T-setbi_5</transition>
                  </is-fireable>
                </negation>
                <conjunction>
                  <is-fireable>
                    <transition>T-sety0_23</transition>
                  </is-fireable>
                  <is-fireable>
                    <transition>T-sety_9</transition>
                  </is-fireable>
                </conjunction>
              </disjunction>
              <all-paths>
                <finally>
                  <is-fireable>
                    <transition>T-forod_13</transition>
                  </is-fireable>
                </finally>
              </all-paths>
            </disjunction>
          </globally>
        </exists-path>
        <is-fireable>
          <transition>T-await_13</transition>
        </is-fireable>
      </disjunction>
    </formula>
  </property>
  <property>
    <id>LamportFastMutEx-COL-8-CTLFireability-10</id>
    <description>Automatically generated</description>
    <formula>
      <negation>
        <exists-path>
          <next>
            <negation>
              <exists-path>
                <finally>
                  <is-fireable>
                    <transition>T-setbi_5</transition>
                  </is-fireable>
                </finally>
              </exists-path>
            </negation>
          </next>
        </exists-path>
      </negation>
    </formula>
  </property>
  <property>
    <id>LamportFastMutEx-COL-8-CTLFireability-11</id>
    <description>Automatically generated</description>
    <formula>
      <exists-path>
        <finally>
          <is-fireable>
            <transition>T-setbi_5</transition>
          </is-fireable>
        </finally>
      </exists-path>
    </formula>
  </property>
  <property>
    <id>LamportFastMutEx-COL-8-CTLFireability-12</id>
    <description>Automatically generated</description>
    <formula>
      <negation>
        <negation>
          <all-paths>
            <finally>
              <conjunction>
                <is-fireable>
                  <transition>T-ynei_15</transition>
                </is-fireable>
                <disjunction>
                  <is-fireable>
                    <transition>T-await_13</transition>
                  </is-fireable>
                  <is-fireable>
                    <transition>T-sety0_23</transition>
                  </is-fireable>
                </disjunction>
              </conjunction>
            </finally>
          </all-paths>
        </negation>
      </negation>
    </formula>
  </property>
  <property>
    <id>LamportFastMutEx-COL-8-CTLFireability-13</id>
    <description>Automatically generated</description>
    <formula>
      <all-paths>
        <finally>
          <conjunction>
            <all-paths>
              <finally>
                <is-fireable>
                  <transition>T-sety_9</transition>
                </is-fireable>
              </finally>
            </all-paths>
            <is-fireable>
              <transition>T-await_13</transition>
            </is-fireable>
          </conjunction>
        </finally>
      </all-paths>
    </formula>
  </property>
  <property>
    <id>LamportFastMutEx-COL-8-CTLFireability-14</id>
    <description>Automatically generated</description>
    <formula>
      <negation>
        <negation>
          <all-paths>
            <finally>
              <all-paths>
                <globally>
                  <is-fireable>
                    <transition>T-sety0_23</transition>
                  </is-fireable>
                </globally>
              </all-paths>
            </finally>
          </all-paths>
        </negation>
      </negation>
    </formula>
  </property>
  <property>
    <id>LamportFastMutEx-COL-8-CTLFireability-15</id>
    <description>Automatically generated</description>
    <formula>
      <all-paths>
        <finally>
          <conjunction>
            <negation>
              <disjunction>
                <negation>
                  <is-fireable>
                    <transition>T-ynei_15</transition>
                  </is-fireable>
                </negation>
                <is-fireable>
                  <transition>T-yeqi_15</transition>
                </is-fireable>
              </disjunction>
            </negation>
            <conjunction>
              <conjunction>
                <negation>
                  <is-fireable>
                    <transition>T-sety0_23</transition>
                  </is-fireable>
                </negation>
                <is-fireable>
                  <transition>T-xnei_10</transition>
                </is-fireable>
              </conjunction>
              <disjunction>
                <disjunction>
                  <is-fireable>
                    <transition>T-setbi_11</transition>
                  </is-fireable>
                  <is-fireable>
                    <transition>T-xeqi_10</transition>
                  </is-fireable>
                </disjunction>
                <disjunction>
                  <is-fireable>
                    <transition>T-setx_3</transition>
                  </is-fireable>
                  <is-fireable>
                    <transition>T-yeqi_15</transition>
                  </is-fireable>
                </disjunction>
              </disjunction>
            </conjunction>
          </conjunction>
        </finally>
      </all-paths>
    </formula>
  </property>
</property-set>
